falcon_filtering/__init__.py
falcon_filtering/filtering_hook.py
falcon_filtering-0.2.0.dist-info/LICENSE
falcon_filtering-0.2.0.dist-info/METADATA
falcon_filtering-0.2.0.dist-info/WHEEL
falcon_filtering-0.2.0.dist-info/top_level.txt
falcon_filtering-0.2.0.dist-info/RECORD
