Metadata-Version: 2.1
Name: falcon-filtering
Version: 0.2.0
Summary: Falcon filtering helper
Home-page: https://github.com/darkheir/falcon-filtering-hook
Author: Raphael Cohen
Author-email: raphael.cohen.utt@gmail.com
License: MIT
Keywords: falcon filtering filter filters api
Platform: UNKNOWN
Classifier: Development Status :: 5 - Production/Stable
Classifier: Intended Audience :: Developers
Classifier: Operating System :: OS Independent
Classifier: Programming Language :: Python
Classifier: Programming Language :: Python :: 3
Classifier: Programming Language :: Python :: 3.6
Classifier: Topic :: Software Development :: Libraries
Requires-Dist: falcon (>=0.3)
